{
    "en": {
      "language": "English",
      "title": "Children's Tales",
      "characterLabel": "Main character's name:",
      "storyTypeLabel": "Story type:",
      "storyLabel": "Story:",
      "storyTypeLabelAdventure": "Adventure",
      "storyTypeLabelFantastic": "Fantastic",
      "storyTypeLabelTerror": "Horror",
      "storyTypeLabelSciFi": "Science fiction",
      "storyTypeLabelRomantic": "Romantic",
      "storyTypeLabelMystery": "Mystery",
      "storyTypeLabelPrincess": "Princesses",
      "storyTypePlane": "Wright Brother",
      "storyTypeApolo": "Apolo 11",
      "storyTypeSteam": "Steam machine",
      "storyTypeColumbus": "Columbus",
      "moralCheckbox": "Finish with a moral",
      "generateButton": "Create",
      "loadingLabel": "Loading...",
      "startButton": "Start",
      "newStoryOptionLabel": "New Story",
      "quickStoryOptionLabel": "Quick Story",
      "trueStoryOptionLabel": "True Story",
      "credits": "Credits",
      "contactUs": "Contact us",
      "name": "Name",
      "email": "Email",
      "message": "Message",
      "send": "Send",
      "maxCounter": "characters left"
    },
    "es": {
      "language": "Español",
      "title": "Cuentos infantiles",
      "characterLabel": "Nombre del personaje principal:",
      "storyTypeLabel": "Tipo de cuento:",
      "storyLabel": "Historia:",
      "storyTypeLabelAdventure": "Aventura",
      "storyTypeLabelFantastic": "Fantástico",
      "storyTypeLabelTerror": "Terror",
      "storyTypeLabelSciFi": "Ciencia ficción",
      "storyTypeLabelRomantic": "Romántico",
      "storyTypeLabelMystery": "Misterio",
      "storyTypeLabelPrincess": "Princesas",
      "storyTypePlane": "Hermanos Wright",
      "storyTypeApolo": "Apolo 11",
      "storyTypeSteam": "Máquina de vapor",
      "storyTypeColumbus": "Cristóbal Colón",
      "moralCheckbox": "Finalizar con una moraleja",
      "generateButton": "Crear",
      "loadingLabel": "Cargando...",
      "startButton": "Comenzar",
      "newStoryOptionLabel": "Nueva Historia",
      "quickStoryOptionLabel": "Historia Rápida",
      "trueStoryOptionLabel": "Historia Real",
      "credits": "Créditos",
      "contactUs": "Contáctanos",
      "name": "Nombre",
      "email": "Email",
      "message": "Mensaje",
      "send": "Enviar",
      "maxCounter": "caracteres restantes"
    },
    "fr": {
      "language": "Français",
      "title": "Contes pour enfants",
      "characterLabel": "Nom du personnage principal :",
      "storyTypeLabel": "Type de conte :",
      "storyLabel": "Conte:",
      "storyTypeLabelAdventure": "Aventure",
      "storyTypeLabelFantastic": "Fantastique",
      "storyTypeLabelTerror": "Horreur",
      "storyTypeLabelSciFi": "Science-fiction",
      "storyTypeLabelRomantic": "Romantique",
      "storyTypeLabelMystery": "Mystère",
      "storyTypeLabelPrincess": "Princesses",
      "storyTypePlane": "Frères Wright",
      "storyTypeApolo": "Apollo 11",
      "storyTypeSteam": "Machine à vapeur",
      "storyTypeColumbus": "Christophe Colomb",
      "moralCheckbox": "Terminer avec une morale",
      "generateButton": "Créer",
      "loadingLabel": "Chargement en cours...",
      "startButton": "Début",
      "newStoryOptionLabel": "Nouvelle Histoire",
      "quickStoryOptionLabel": "Histoire rapide",
      "trueStoryOptionLabel": "Histoire Vraie",
      "credits": "Crédits",
      "contactUs": "Contactez-nous",
      "name": "Nom",
      "email": "Email",
      "message": "Message",
      "send": "Envoyer",
      "maxCounter": "caractères restants"
    },
    "pt": {
      "language": "Português",
      "title": "Contos infantis",
      "characterLabel": "Nome do personagem principal:",
      "storyTypeLabel": "Tipo de história:",
      "storyLabel": "História:",
      "storyTypeLabelAdventure": "Aventura",
      "storyTypeLabelFantastic": "Fantástico",
      "storyTypeLabelTerror": "Terror",
      "storyTypeLabelSciFi": "Ficção científica",
      "storyTypeLabelRomantic": "Romântico",
      "storyTypeLabelMystery": "Mistério",
      "storyTypeLabelPrincess": "Princesas",
      "storyTypePlane": "Irmãos Wright",
      "storyTypeApolo": "Apolo 11",
      "storyTypeSteam": "Máquina a vapor",
      "storyTypeColumbus": "Colombo",
      "moralCheckbox": "Terminar com uma moral",
      "generateButton": "Criar",
      "loadingLabel": "Carregando...",
      "startButton": "Início",
      "newStoryOptionLabel": "Nova História",
      "quickStoryOptionLabel": "História rápida",
      "trueStoryOptionLabel": "História Verdadeira",
      "credits": "Créditos",
      "contactUs": "Contate-nos",
      "name": "Nome",
      "email": "Email",
      "message": "Mensagem",
      "send": "Enviar",
      "maxCounter": "caracteres restantes"
    },
    "de": {
      "language": "Deutsch",
      "title": "Kinder-Geschichten",
      "characterLabel": "Name der Hauptfigur:",
      "storyTypeLabel": "Geschichtentyp:",
      "storyLabel": "Geschichte:",
      "storyTypeLabelAdventure": "Abenteuer",
      "storyTypeLabelFantastic": "Fantastisch",
      "storyTypeLabelTerror": "Horror",
      "storyTypeLabelSciFi": "Science-Fiction",
      "storyTypeLabelRomantic": "Romantisch",
      "storyTypeLabelMystery": "Mysteriös",
      "storyTypeLabelPrincess": "Prinzessinnen",
      "storyTypePlane": "Wright-Brüder",
      "storyTypeApolo": "Apollo 11",
      "storyTypeSteam": "Dampfmaschine",
      "storyTypeColumbus": "Christoph Kolumbus",
      "moralCheckbox": "Mit einer Moral beenden",
      "generateButton": "Erstellen",
      "loadingLabel": "Laden...",
      "startButton": "Start",
      "newStoryOptionLabel": "Neue Geschichte",
      "quickStoryOptionLabel": "Schnelle Geschichte",
      "trueStoryOptionLabel": "Wahre Geschichte",
      "credits": "Gutschrift",
      "contactUs": "Kontaktieren Sie uns",
      "name": "Name",
      "email": "E-Mail",
      "message": "Nachricht",
      "send": "Senden",
      "maxCounter": "Zeichen übrig"
    },
    "it": {
      "language": "Italiano",
      "title": "Fiabe per bambini",
      "characterLabel": "Nome del personaggio principale:",
      "storyTypeLabel": "Tipo di storia:",
      "storyLabel": "Storia:",
      "storyTypeLabelAdventure": "Avventura",
      "storyTypeLabelFantastic": "Fantastica",
      "storyTypeLabelTerror": "Horror",
      "storyTypeLabelSciFi": "Fantascienza",
      "storyTypeLabelRomantic": "Romantica",
      "storyTypeLabelMystery": "Mistero",
      "storyTypeLabelPrincess": "Principesse",
      "storyTypePlane": "Fratelli Wright",
      "storyTypeApolo": "Apollo 11",
      "storyTypeSteam": "Macchina a vapore",
      "storyTypeColumbus": "Colombo",
      "moralCheckbox": "Concludere con una morale",
      "generateButton": "Creare",
      "loadingLabel": "Caricamento...",
      "startButton": "Inizio",
      "newStoryOptionLabel": "Nuova Storia",
      "quickStoryOptionLabel": "Storia rapida",
      "trueStoryOptionLabel": "Storia Vera",
      "credits": "Crediti",
      "contactUs": "Contattaci",
      "name": "Nome",
      "email": "Email",
      "message": "Messaggio",
      "send": "Invia",
      "maxCounter": "caratteri rimasti"
    }
}
  